Workbook

Sheet Notes
A1: How to read this workbook
A2: Blue text = values typed from your two Excel files. Black = formulas. Green = links to another sheet. Yellow fill = needs your attention.
A4: What was cleaned from your files
A5: Percent signs and the letter c were removed so every number is numeric. Increases are stored as percentages (27.5% is 0.275).
A6: Tariff sources now name the documents I could read (see the Sources sheet). Your Verified flags are kept exactly as you set them.
A7: CPI figures 2008 to 2025 were checked against Stats SA's CPI history table (P0141, Table B2, annual average) and the source is recorded. Yellow cells in the CPI sheet were changed from your file; the difference column shows by how much.
A9: Items to resolve before you publish
A10: 1. CPI 2008: Stats SA's headline annual average is 11.5%. Your file's 9.9% does not match an annual figure I could find (December 2008 year-on-year was 9.5%). 11.5% is used.
A11: 2. CPI 2009, 2013, 2018 and 2021 differ by 0.1 point from your file and were set to the Stats SA values (7.1, 5.7, 4.7, 4.5).
A12: 3. CPI 2026 is your projected figure, not a completed annual average, so it is excluded from the comparison.
A13: 4. Tariff evidence: only 2022/23 is backed by a primary Eskom document. Most other years are cross-checked across two or more secondary sources. Years to confirm in a NERSA decision or an Eskom tariff book: 2013 (single source), 2014, 2017 and 2020 (not confirmed), 2021 (sources conflict: 15.63 vs 15.06), 2016 and 2019 (single source).
A14: 5. Some increases took effect part-way through the financial year (for example 2008 and 1 July 2009). Direct customers (April) and municipal customers (July) also get different increases, for example 9.61% and 8.61% in 2022/23. This series is the direct-customer average increase.
... A21: Each financial year is compared with CPI for the calendar year in which it starts (Settings, CPI year offset = 0).

Sheet Summary
A1: Measure | B1: Value | C1: How it is calculated
A2: Years compared | B2: =COUNT(Comparison!C2:C19) -> 18 | C2: Number of financial years in the Comparison sheet.
A3: Years tariff increase was above CPI | B3: =COUNTIF(Comparison!F2:F19,"Yes") -> 17 | C3: Count of Yes in the Comparison sheet.
A4: Tariff: total growth | B4: =Comparison!G19/Settings!B2-1 -> 9.5392168 | C4: Final tariff index divided by 100, minus 1.
A5: CPI: total growth | B5: =Comparison!H19/Settings!B2-1 -> 1.6071842 | C5: Final CPI index divided by 100, minus 1.
A6: Tariff: average growth per year (CAGR) | B6: =(Comparison!G19/Settings!B2)^(1/B2)-1 -> 0.13978434 | C6: (end / start) to the power 1/years, minus 1.
A7: CPI: average growth per year (CAGR) | B7: =(Comparison!H19/Settings!B2)^(1/B2)-1 -> 0.054679854 | C7: Same formula for CPI.
A8: Average yearly gap (percentage points) | B8: =AVERAGE(Comparison!E2:E19) -> 8.7716667 | C8: Simple average of the yearly gaps.
A9: Real tariff index at end of period | B9: =Comparison!I19 -> 404.23753 | C9: Tariff index / CPI index x 100. Above 100 means tariffs outran prices.

Sheet Tariff increases
A1: FY start year | B1: Financial year | C1: Approved average increase | D1: Value in your file | E1: Difference (percentage points) | F1: Average price (c/kWh) | G1: Evidence found | H1: Sources read | I1: Verified (your flag) | J1: Note
A2: 2008 | B2: =A2&"/"&RIGHT(A2+1,2) -> 2008/09 | C2: 0.275 | D2: 0.275 | E2: =(C2-D2)*100 -> 0 | F2: 25 | G2: Cross-checked (2+ secondary) | H2: M&G 25 Jun 2008; Our Power | I2: =TRUE() -> TRUE | J2: Took effect part-way through the year.
A3: 2009 | B3: =A3&"/"&RIGHT(A3+1,2) -> 2009/10 | C3: 0.313 | D3: 0.313 | E3: =(C3-D3)*100 -> 0 | F3: 33 | G3: Cross-checked (2+ secondary) | H3: M&G 25 Jun 2009; Our Power | I3: =TRUE() -> TRUE | J3: Effective 1 July 2009 (mid-year).
A4: 2010 | B4: =A4&"/"&RIGHT(A4+1,2) -> 2010/11 | C4: 0.248 | D4: 0.248 | E4: =(C4-D4)*100 -> 0 | F4: 41 | G4: Cross-checked (2+ secondary) | H4: Business Times 10 Mar 2019; MyBroadband (Eskom tariff books); Our Power | I4: =TRUE() -> TRUE
A5: 2011 | B5: =A5&"/"&RIGHT(A5+1,2) -> 2011/12 | C5: 0.258 | D5: 0.258 | E5: =(C5-D5)*100 -> 0 | F5: 52 | G5: Cross-checked (2+ secondary) | H5: Business Times 10 Mar 2019; Our Power | I5: =TRUE() -> TRUE | J5: MyBroadband shows a 25.20% average price increase, a different measure.
A6: 2012 | B6: =A6&"/"&RIGHT(A6+1,2) -> 2012/13 | C6: 0.16 | D6: 0.16 | E6: =(C6-D6)*100 -> 0 | F6: 60 | G6: Cross-checked (2+ secondary) | H6: Business Times 10 Mar 2019; Our Power | I6: =TRUE() -> TRUE | J6: Approved as 25.9% then revised to 16%.
A7: 2013 | B7: =A7&"/"&RIGHT(A7+1,2) -> 2013/14 | C7: 0.08 | D7: 0.08 | E7: =(C7-D7)*100 -> 0 | F7: 65 | G7: Single secondary source | H7: Our Power | I7: =TRUE() -> TRUE | J7: Confirm in a NERSA decision or Eskom tariff book.
A8: 2014 | B8: =A8&"/"&RIGHT(A8+1,2) -> 2014/15 | C8: 0.08 | D8: 0.08 | E8: =(C8-D8)*100 -> 0 | F8: 70 | G8: Not confirmed | H8: Not confirmed in sources read | I8: =TRUE() -> TRUE | J8: Needs a source.
A9: 2015 | B9: =A9&"/"&RIGHT(A9+1,2) -> 2015/16 | C9: 0.1269 | D9: 0.127 | E9: =(C9-D9)*100 -> -0.01 | F9: 79 | G9: Cross-checked (2+ secondary) | H9: BusinessTech compilation; Citizen (2016) | I9: =TRUE() -> TRUE | J9: Two decimals taken from those sources; your file had 12.7.
A10: 2016 | B10: =A10&"/"&RIGHT(A10+1,2) -> 2016/17 | C10: 0.094 | D10: 0.094 | E10: =(C10-D10)*100 -> 0 | F10: 86 | G10: Single secondary source | H10: Citizen (2016) | I10: =TRUE() -> TRUE
A11: 2017 | B11: =A11&"/"&RIGHT(A11+1,2) -> 2017/18 | C11: 0.022 | D11: 0.022 | E11: =(C11-D11)*100 -> 0 | F11: 88 | G11: Not confirmed | H11: Not confirmed in sources read | I11: =TRUE() -> TRUE | J11: Needs a source. Municipal increase that year was about 0.3% (Stats SA).
A12: 2018 | B12: =A12&"/"&RIGHT(A12+1,2) -> 2018/19 | C12: 0.0523 | D12: 0.052 | E12: =(C12-D12)*100 -> 0.03 | F12: 93 | G12: Cross-checked (2+ secondary) | H12: Sowetan 9 Sep 2026; SavePower; Our Power | I12: =TRUE() -> TRUE | J12: NERSA approved 5.23% in Dec 2017; your file had 5.2.
A13: 2019 | B13: =A13&"/"&RIGHT(A13+1,2) -> 2019/20 | C13: 0.094 | D13: 0.094 | E13: =(C13-D13)*100 -> 0 | F13: 102 | G13: Single secondary source | H13: Business Times 10 Mar 2019 | I13: =TRUE() -> TRUE
A14: 2020 | B14: =A14&"/"&RIGHT(A14+1,2) -> 2020/21 | C14: 0.069 | D14: 0.069 | E14: =(C14-D14)*100 -> 0 | F14: 109 | G14: Conflict or not confirmed | H14: Not confirmed in sources read | I14: =TRUE() -> TRUE | J14: Business Times (2019) reported 8.1% for 2020/21. Confirm which applied.
A15: 2021 | B15: =A15&"/"&RIGHT(A15+1,2) -> 2021/22 | C15: 0.1563 | D15: 0.156 | E15: =(C15-D15)*100 -> 0.03 | F15: 126 | G15: Sources conflict | H15: PowerOptimal 2022; (SavePower shows 15.06) | I15: =TRUE() -> TRUE | J15: 15.63% used (two decimals from PowerOptimal); SavePower lists 15.06%. Confirm in Eskom's tariff book.
A16: 2022 | B16: =A16&"/"&RIGHT(A16+1,2) -> 2022/23 | C16: 0.0961 | D16: 0.096 | E16: =(C16-D16)*100 -> 0.01 | F16: 138 | G16: Primary document | H16: Eskom Tariff Booklet 2022/23; Sowetan; PowerOptimal; SavePower | I16: =TRUE() -> TRUE | J16: Direct customers from 1 April 2022; municipal increase was 8.61% from 1 July 2022.
A17: 2023 | B17: =A17&"/"&RIGHT(A17+1,2) -> 2023/24 | C17: 0.1865 | D17: 0.187 | E17: =(C17-D17)*100 -> -0.05 | F17: 164 | G17: Cross-checked (2+ secondary) | H17: Sowetan 9 Sep 2026; News24 12 Jan 2023; SavePower | I17: =TRUE() -> TRUE | J17: Your file had 18.7.
A18: 2024 | B18: =A18&"/"&RIGHT(A18+1,2) -> 2024/25 | C18: 0.1274 | D18: 0.1274 | E18: =(C18-D18)*100 -> 0 | F18: 185 | G18: Cross-checked (2+ secondary) | H18: Sowetan 9 Sep 2026; News24 12 Jan 2023 | I18: =TRUE() -> TRUE
A19: 2025 | B19: =A19&"/"&RIGHT(A19+1,2) -> 2025/26 | C19: 0.1274 | D19: 0.1274 | E19: =(C19-D19)*100 -> 0 | F19: 208 | G19: Cross-checked (2+ secondary) | H19: Engineering News 30 Jan 2025; Business Report (Feb 2025) | I19: =TRUE() -> TRUE
A20: 2026 | B20: =A20&"/"&RIGHT(A20+1,2) -> 2026/27 | C20: 0.0876 | D20: 0.0876 | E20: =(C20-D20)*100 -> 0 | F20: 226 | G20: Cross-checked (2+ secondary) | H20: Engineering News 10 Mar 2026; Daily Investor 2026 | I20: =TRUE() -> TRUE | J20: Effective 1 April 2026. Excluded from the comparison (CPI 2026 incomplete). Average price definitions differ: Our Power lists 234 c/kWh and Daily Investor about 241.6 c/kWh (Mar 2026). Not used in the analysis.

Sheet CPI
A1: Calendar year | B1: Annual average CPI inflation | C1: Source | D1: Verified | E1: Value in your file | F1: Difference (percentage points) | G1: Note
A2: 2008 | B2: 0.115 | C2: Stats SA P0141 CPI history, Table B2 (annual average) | D2: =TRUE() -> TRUE | E2: 0.099 | F2: =(B2-E2)*100 -> 1.6 | G2: Stats SA headline annual average is 11.5. Your file also listed 9.9, which is not an annual average I could match (December 2008 year-on-year was 9.5). Global Financial Crisis food/fuel shock
A3: 2009 | B3: 0.071 | C3: Stats SA P0141 CPI history, Table B2 (annual average) | D3: =TRUE() -> TRUE | E3: 0.072 | F3: =(B3-E3)*100 -> -0.1 | G3: Corrected from 7.2 in your file to 7.1 to match Stats SA. Post-recession recovery
A4: 2010 | B4: 0.043 | C4: Stats SA P0141 CPI history, Table B2 (annual average) | D4: =TRUE() -> TRUE | E4: 0.043 | F4: =(B4-E4)*100 -> 0 | G4: World Cup year, inflation slows down
A5: 2011 | B5: 0.05 | C5: Stats SA P0141 CPI history, Table B2 (annual average) | D5: =TRUE() -> TRUE | E5: 0.05 | F5: =(B5-E5)*100 -> 0 | G5: Steady recovery period
A6: 2012 | B6: 0.056 | C6: Stats SA P0141 CPI history, Table B2 (annual average) | D6: =TRUE() -> TRUE | E6: 0.056 | F6: =(B6-E6)*100 -> 0 | G6: Moderate inflation
A7: 2013 | B7: 0.057 | C7: Stats SA P0141 CPI history, Table B2 (annual average) | D7: =TRUE() -> TRUE | E7: 0.058 | F7: =(B7-E7)*100 -> -0.1 | G7: Corrected from 5.8 in your file to 5.7 to match Stats SA. SARB target boundary pressure
A8: 2014 | B8: 0.061 | C8: Stats SA P0141 CPI history, Table B2 (annual average) | D8: =TRUE() -> TRUE | E8: 0.061 | F8: =(B8-E8)*100 -> 0 | G8: Food & transport price pressure
A9: 2015 | B9: 0.046 | C9: Stats SA P0141 CPI history, Table B2 (annual average) | D9: =TRUE() -> TRUE | E9: 0.046 | F9: =(B9-E9)*100 -> 0 | G9: Global oil price drops
A10: 2016 | B10: 0.064 | C10: Stats SA P0141 CPI history, Table B2 (annual average) | D10: =TRUE() -> TRUE | E10: 0.064 | F10: =(B10-E10)*100 -> 0 | G10: Severe regional drought shock
A11: 2017 | B11: 0.053 | C11: Stats SA P0141 CPI history, Table B2 (annual average) | D11: =TRUE() -> TRUE | E11: 0.053 | F11: =(B11-E11)*100 -> 0 | G11: SARB shifts focus to 4.5% midpoint
A12: 2018 | B12: 0.047 | C12: Stats SA P0141 CPI history, Table B2 (annual average) | D12: =TRUE() -> TRUE | E12: 0.046 | F12: =(B12-E12)*100 -> 0.1 | G12: Corrected from 4.6 in your file to 4.7 to match Stats SA. Moderate inflation
A13: 2019 | B13: 0.041 | C13: Stats SA P0141 CPI history, Table B2 (annual average) | D13: =TRUE() -> TRUE | E13: 0.041 | F13: =(B13-E13)*100 -> 0 | G13: Subdued economic growth
... A19: 2025 | B19: 0.032 | C19: Stats SA P0141 CPI history, Table B2 (annual average) | D19: =TRUE() -> TRUE | E19: 0.032 | F19: =(B19-E19)*100 -> 0 | G19: Lowest average inflation rate in decades
A20: 2026 | B20: 0.041 | C20: Your file (projection) | D20: =FALSE() -> FALSE | E20: 0.041 | F20: =(B20-E20)*100 -> 0 | G20: Projected, not a completed annual average; not used in the comparison. Stats SA monthly rates for Jan to Sep 2026 average about 4.0. Current projected average

Sheet Settings
A1: Setting | B1: Value | C1: Meaning
A2: Index starting level | B2: 100 | C2: Index is 100 just before the first financial year (Apr 2008).
A3: Last financial year compared (start year) | B3: 2025 | C3: FY2025/26. CPI for calendar 2026 is not complete until early 2027, so the comparison stops here.
A4: CPI year offset | B4: 0 | C4: 0 = compare each FY with CPI for the calendar year in which it starts; 1 = year in which it ends.

Sheet Comparison
A1: FY start year | B1: Financial year | C1: Tariff increase | D1: CPI inflation | E1: Gap (percentage points) | F1: Tariff above CPI? | G1: Tariff index | H1: CPI index | I1: Real tariff index
A2: ='Tariff increases'!A2 -> 2008 | B2: ='Tariff increases'!B2 -> 2008/09 | C2: ='Tariff increases'!C2 -> 0.275 | D2: =INDEX(CPI!$B$2:$B$20,MATCH(A2+Settings!$B$4,CPI!$A$2:$A$20,0)) -> 0.115 | E2: =(C2-D2)*100 -> 16 | F2: =IF(C2>D2,"Yes","No") -> Yes | G2: =Settings!$B$2*(1+C2) -> 127.5 | H2: =Settings!$B$2*(1+D2) -> 111.5 | I2: =G2/H2*Settings!$B$2 -> 114.34978
A3: ='Tariff increases'!A3 -> 2009 | B3: ='Tariff increases'!B3 -> 2009/10 | C3: ='Tariff increases'!C3 -> 0.313 | D3: =INDEX(CPI!$B$2:$B$20,MATCH(A3+Settings!$B$4,CPI!$A$2:$A$20,0)) -> 0.071 | E3: =(C3-D3)*100 -> 24.2 | F3: =IF(C3>D3,"Yes","No") -> Yes | G3: =G2*(1+C3) -> 167.4075 | H3: =H2*(1+D3) -> 119.4165 | I3: =G3/H3*Settings!$B$2 -> 140.18791
A4: ='Tariff increases'!A4 -> 2010 | B4: ='Tariff increases'!B4 -> 2010/11 | C4: ='Tariff increases'!C4 -> 0.248 | D4: =INDEX(CPI!$B$2:$B$20,MATCH(A4+Settings!$B$4,CPI!$A$2:$A$20,0)) -> 0.043 | E4: =(C4-D4)*100 -> 20.5 | F4: =IF(C4>D4,"Yes","No") -> Yes | G4: =G3*(1+C4) -> 208.92456 | H4: =H3*(1+D4) -> 124.55141 | I4: =G4/H4*Settings!$B$2 -> 167.74163
A5: ='Tariff increases'!A5 -> 2011 | B5: ='Tariff increases'!B5 -> 2011/12 | C5: ='Tariff increases'!C5 -> 0.258 | D5: =INDEX(CPI!$B$2:$B$20,MATCH(A5+Settings!$B$4,CPI!$A$2:$A$20,0)) -> 0.05 | E5: =(C5-D5)*100 -> 20.8 | F5: =IF(C5>D5,"Yes","No") -> Yes | G5: =G4*(1+C5) -> 262.8271 | H5: =H4*(1+D5) -> 130.77898 | I5: =G5/H5*Settings!$B$2 -> 200.97044
A6: ='Tariff increases'!A6 -> 2012 | B6: ='Tariff increases'!B6 -> 2012/13 | C6: ='Tariff increases'!C6 -> 0.16 | D6: =INDEX(CPI!$B$2:$B$20,MATCH(A6+Settings!$B$4,CPI!$A$2:$A$20,0)) -> 0.056 | E6: =(C6-D6)*100 -> 10.4 | F6: =IF(C6>D6,"Yes","No") -> Yes | G6: =G5*(1+C6) -> 304.87943 | H6: =H5*(1+D6) -> 138.1026 | I6: =G6/H6*Settings!$B$2 -> 220.76299
A7: ='Tariff increases'!A7 -> 2013 | B7: ='Tariff increases'!B7 -> 2013/14 | C7: ='Tariff increases'!C7 -> 0.08 | D7: =INDEX(CPI!$B$2:$B$20,MATCH(A7+Settings!$B$4,CPI!$A$2:$A$20,0)) -> 0.057 | E7: =(C7-D7)*100 -> 2.3 | F7: =IF(C7>D7,"Yes","No") -> Yes | G7: =G6*(1+C7) -> 329.26979 | H7: =H6*(1+D7) -> 145.97445 | I7: =G7/H7*Settings!$B$2 -> 225.56672
A8: ='Tariff increases'!A8 -> 2014 | B8: ='Tariff increases'!B8 -> 2014/15 | C8: ='Tariff increases'!C8 -> 0.08 | D8: =INDEX(CPI!$B$2:$B$20,MATCH(A8+Settings!$B$4,CPI!$A$2:$A$20,0)) -> 0.061 | E8: =(C8-D8)*100 -> 1.9 | F8: =IF(C8>D8,"Yes","No") -> Yes | G8: =G7*(1+C8) -> 355.61137 | H8: =H7*(1+D8) -> 154.87889 | I8: =G8/H8*Settings!$B$2 -> 229.60609
A9: ='Tariff increases'!A9 -> 2015 | B9: ='Tariff increases'!B9 -> 2015/16 | C9: ='Tariff increases'!C9 -> 0.1269 | D9: =INDEX(CPI!$B$2:$B$20,MATCH(A9+Settings!$B$4,CPI!$A$2:$A$20,0)) -> 0.046 | E9: =(C9-D9)*100 -> 8.09 | F9: =IF(C9>D9,"Yes","No") -> Yes | G9: =G8*(1+C9) -> 400.73845 | H9: =H8*(1+D9) -> 162.00332 | I9: =G9/H9*Settings!$B$2 -> 247.36434
A10: ='Tariff increases'!A10 -> 2016 | B10: ='Tariff increases'!B10 -> 2016/17 | C10: ='Tariff increases'!C10 -> 0.094 | D10: =INDEX(CPI!$B$2:$B$20,MATCH(A10+Settings!$B$4,CPI!$A$2:$A$20,0)) -> 0.064 | E10: =(C10-D10)*100 -> 3 | F10: =IF(C10>D10,"Yes","No") -> Yes | G10: =G9*(1+C10) -> 438.40787 | H10: =H9*(1+D10) -> 172.37153 | I10: =G10/H10*Settings!$B$2 -> 254.3389
A11: ='Tariff increases'!A11 -> 2017 | B11: ='Tariff increases'!B11 -> 2017/18 | C11: ='Tariff increases'!C11 -> 0.022 | D11: =INDEX(CPI!$B$2:$B$20,MATCH(A11+Settings!$B$4,CPI!$A$2:$A$20,0)) -> 0.053 | E11: =(C11-D11)*100 -> -3.1 | F11: =IF(C11>D11,"Yes","No") -> No | G11: =G10*(1+C11) -> 448.05284 | H11: =H10*(1+D11) -> 181.50723 | I11: =G11/H11*Settings!$B$2 -> 246.85124
A12: ='Tariff increases'!A12 -> 2018 | B12: ='Tariff increases'!B12 -> 2018/19 | C12: ='Tariff increases'!C12 -> 0.0523 | D12: =INDEX(CPI!$B$2:$B$20,MATCH(A12+Settings!$B$4,CPI!$A$2:$A$20,0)) -> 0.047 | E12: =(C12-D12)*100 -> 0.53 | F12: =IF(C12>D12,"Yes","No") -> Yes | G12: =G11*(1+C12) -> 471.486 | H12: =H11*(1+D12) -> 190.03807 | I12: =G12/H12*Settings!$B$2 -> 248.10082
A13: ='Tariff increases'!A13 -> 2019 | B13: ='Tariff increases'!B13 -> 2019/20 | C13: ='Tariff increases'!C13 -> 0.094 | D13: =INDEX(CPI!$B$2:$B$20,MATCH(A13+Settings!$B$4,CPI!$A$2:$A$20,0)) -> 0.041 | E13: =(C13-D13)*100 -> 5.3 | F13: =IF(C13>D13,"Yes","No") -> Yes | G13: =G12*(1+C13) -> 515.80569 | H13: =H12*(1+D13) -> 197.82963 | I13: =G13/H13*Settings!$B$2 -> 260.73228
A14: ='Tariff increases'!A14 -> 2020 | B14: ='Tariff increases'!B14 -> 2020/21 | C14: ='Tariff increases'!C14 -> 0.069 | D14: =INDEX(CPI!$B$2:$B$20,MATCH(A14+Settings!$B$4,CPI!$A$2:$A$20,0)) -> 0.033 | E14: =(C14-D14)*100 -> 3.6 | F14: =IF(C14>D14,"Yes","No") -> Yes | G14: =G13*(1+C14) -> 551.39628 | H14: =H13*(1+D14) -> 204.358 | I14: =G14/H14*Settings!$B$2 -> 269.81878
... A19: ='Tariff increases'!A19 -> 2025 | B19: ='Tariff increases'!B19 -> 2025/26 | C19: ='Tariff increases'!C19 -> 0.1274 | D19: =INDEX(CPI!$B$2:$B$20,MATCH(A19+Settings!$B$4,CPI!$A$2:$A$20,0)) -> 0.032 | E19: =(C19-D19)*100 -> 9.54 | F19: =IF(C19>D19,"Yes","No") -> Yes | G19: =G18*(1+C19) -> 1053.9217 | H19: =H18*(1+D19) -> 260.71842 | I19: =G19/H19*Settings!$B$2 -> 404.23753
A21: Rows stop at FY2025/26 (see Settings). Tariff index and CPI index compound each year's increase from 100.

Sheet Checks
A1: FY start year | B1: Average price (c/kWh) | C1: Previous year price | D1: Approved increase | E1: Implied by prices | F1: Lowest allowed by price rounding | G1: Highest allowed by price rounding | H1: Result
A2: ='Tariff increases'!A3 -> 2009 | B2: ='Tariff increases'!F3 -> 33 | C2: ='Tariff increases'!F2 -> 25 | D2: ='Tariff increases'!C3 -> 0.313 | E2: =B2/C2-1 -> 0.32 | F2: =(B2-0.5)/(C2+0.5)-1 -> 0.2745098 | G2: =(B2+0.5)/(C2-0.5)-1 -> 0.36734694 | H2: =IF(AND(D2>=F2,D2<=G2),"OK","CHECK") -> OK
A3: ='Tariff increases'!A4 -> 2010 | B3: ='Tariff increases'!F4 -> 41 | C3: ='Tariff increases'!F3 -> 33 | D3: ='Tariff increases'!C4 -> 0.248 | E3: =B3/C3-1 -> 0.24242424 | F3: =(B3-0.5)/(C3+0.5)-1 -> 0.20895522 | G3: =(B3+0.5)/(C3-0.5)-1 -> 0.27692308 | H3: =IF(AND(D3>=F3,D3<=G3),"OK","CHECK") -> OK
A4: ='Tariff increases'!A5 -> 2011 | B4: ='Tariff increases'!F5 -> 52 | C4: ='Tariff increases'!F4 -> 41 | D4: ='Tariff increases'!C5 -> 0.258 | E4: =B4/C4-1 -> 0.26829268 | F4: =(B4-0.5)/(C4+0.5)-1 -> 0.24096386 | G4: =(B4+0.5)/(C4-0.5)-1 -> 0.2962963 | H4: =IF(AND(D4>=F4,D4<=G4),"OK","CHECK") -> OK
A5: ='Tariff increases'!A6 -> 2012 | B5: ='Tariff increases'!F6 -> 60 | C5: ='Tariff increases'!F5 -> 52 | D5: ='Tariff increases'!C6 -> 0.16 | E5: =B5/C5-1 -> 0.15384615 | F5: =(B5-0.5)/(C5+0.5)-1 -> 0.13333333 | G5: =(B5+0.5)/(C5-0.5)-1 -> 0.17475728 | H5: =IF(AND(D5>=F5,D5<=G5),"OK","CHECK") -> OK
A6: ='Tariff increases'!A7 -> 2013 | B6: ='Tariff increases'!F7 -> 65 | C6: ='Tariff increases'!F6 -> 60 | D6: ='Tariff increases'!C7 -> 0.08 | E6: =B6/C6-1 -> 0.083333333 | F6: =(B6-0.5)/(C6+0.5)-1 -> 0.066115702 | G6: =(B6+0.5)/(C6-0.5)-1 -> 0.10084034 | H6: =IF(AND(D6>=F6,D6<=G6),"OK","CHECK") -> OK
A7: ='Tariff increases'!A8 -> 2014 | B7: ='Tariff increases'!F8 -> 70 | C7: ='Tariff increases'!F7 -> 65 | D7: ='Tariff increases'!C8 -> 0.08 | E7: =B7/C7-1 -> 0.076923077 | F7: =(B7-0.5)/(C7+0.5)-1 -> 0.061068702 | G7: =(B7+0.5)/(C7-0.5)-1 -> 0.093023256 | H7: =IF(AND(D7>=F7,D7<=G7),"OK","CHECK") -> OK
A8: ='Tariff increases'!A9 -> 2015 | B8: ='Tariff increases'!F9 -> 79 | C8: ='Tariff increases'!F8 -> 70 | D8: ='Tariff increases'!C9 -> 0.1269 | E8: =B8/C8-1 -> 0.12857143 | F8: =(B8-0.5)/(C8+0.5)-1 -> 0.11347518 | G8: =(B8+0.5)/(C8-0.5)-1 -> 0.14388489 | H8: =IF(AND(D8>=F8,D8<=G8),"OK","CHECK") -> OK
A9: ='Tariff increases'!A10 -> 2016 | B9: ='Tariff increases'!F10 -> 86 | C9: ='Tariff increases'!F9 -> 79 | D9: ='Tariff increases'!C10 -> 0.094 | E9: =B9/C9-1 -> 0.088607595 | F9: =(B9-0.5)/(C9+0.5)-1 -> 0.075471698 | G9: =(B9+0.5)/(C9-0.5)-1 -> 0.10191083 | H9: =IF(AND(D9>=F9,D9<=G9),"OK","CHECK") -> OK
A10: ='Tariff increases'!A11 -> 2017 | B10: ='Tariff increases'!F11 -> 88 | C10: ='Tariff increases'!F10 -> 86 | D10: ='Tariff increases'!C11 -> 0.022 | E10: =B10/C10-1 -> 0.023255814 | F10: =(B10-0.5)/(C10+0.5)-1 -> 0.011560694 | G10: =(B10+0.5)/(C10-0.5)-1 -> 0.035087719 | H10: =IF(AND(D10>=F10,D10<=G10),"OK","CHECK") -> OK
A11: ='Tariff increases'!A12 -> 2018 | B11: ='Tariff increases'!F12 -> 93 | C11: ='Tariff increases'!F11 -> 88 | D11: ='Tariff increases'!C12 -> 0.0523 | E11: =B11/C11-1 -> 0.056818182 | F11: =(B11-0.5)/(C11+0.5)-1 -> 0.04519774 | G11: =(B11+0.5)/(C11-0.5)-1 -> 0.068571429 | H11: =IF(AND(D11>=F11,D11<=G11),"OK","CHECK") -> OK
A12: ='Tariff increases'!A13 -> 2019 | B12: ='Tariff increases'!F13 -> 102 | C12: ='Tariff increases'!F12 -> 93 | D12: ='Tariff increases'!C13 -> 0.094 | E12: =B12/C12-1 -> 0.096774194 | F12: =(B12-0.5)/(C12+0.5)-1 -> 0.085561497 | G12: =(B12+0.5)/(C12-0.5)-1 -> 0.10810811 | H12: =IF(AND(D12>=F12,D12<=G12),"OK","CHECK") -> OK
A13: ='Tariff increases'!A14 -> 2020 | B13: ='Tariff increases'!F14 -> 109 | C13: ='Tariff increases'!F13 -> 102 | D13: ='Tariff increases'!C14 -> 0.069 | E13: =B13/C13-1 -> 0.068627451 | F13: =(B13-0.5)/(C13+0.5)-1 -> 0.058536585 | G13: =(B13+0.5)/(C13-0.5)-1 -> 0.078817734 | H13: =IF(AND(D13>=F13,D13<=G13),"OK","CHECK") -> OK
... A19: ='Tariff increases'!A20 -> 2026 | B19: ='Tariff increases'!F20 -> 226 | C19: ='Tariff increases'!F19 -> 208 | D19: ='Tariff increases'!C20 -> 0.0876 | E19: =B19/C19-1 -> 0.086538462 | F19: =(B19-0.5)/(C19+0.5)-1 -> 0.081534772 | G19: =(B19+0.5)/(C19-0.5)-1 -> 0.091566265 | H19: =IF(AND(D19>=F19,D19<=G19),"OK","CHECK") -> OK
A21: Prices are rounded to the nearest cent, so the increase implied by two prices is only accurate within a range. OK means your approved increase falls inside that range.

Sheet Sources
A1: No. | B1: Source | C1: Type | D1: Used for | E1: URL | F1: Date accessed | G1: Note
A2: 1 | B2: Stats SA P0141 CPI history, Table B2 (headline CPI year-on-year, Average column) | C2: Primary | D2: Annual average CPI 2008 to 2025; 2026 partial | E2: https://www.statssa.gov.za/publications/P0141/CPIHistory.pdf?SCH=73815 | F2: 29 Oct 2026 | G2: Footnotes: primary urban areas to Dec 2008, all urban areas from Jan 2009; compilation changes in Jan 2009.
A3: 2 | B3: Stats SA P0141 CPI release, May 2008 | C3: Primary | D3: 2008 context: headline vs CPIX monthly rates | E3: https://statssa.gov.za/publications/P0141/P0141May2008.pdf | F3: 29 Oct 2026 | G3: CPIX was the inflation-target measure in 2008.
A4: 3 | B4: Eskom Tariffs and Charges Booklet 2022/23 | C4: Primary | D4: 2022/23 increase: 9.61% direct customers (municipal 8.61% from 1 Jul 2022) | E4: https://www.eskom.co.za/distribution/wp-content/uploads/2022/05/4756-ESKOM-Tariff-Booklet-2022-Final-Rev.pdf | F4: 29 Oct 2026 | G4: Shows direct and municipal increases differ.
A5: 4 | B5: Mail & Guardian, 25 Jun 2008, May CPIX jumps to 10,9% | C5: Secondary | D5: 2008/09: Eskom allowed 27.5% on average | E5: https://mg.co.za/business/2008-06-25-may-cpix-jumps-to-10-9/ | F5: 29 Oct 2026 | G5: Report of the NERSA decision.
A6: 5 | B6: Mail & Guardian, 25 Jun 2009, Eskom granted a 31.3% tariff increase | C6: Secondary | D6: 2009/10: 31.3% | E6: https://mg.co.za/article/2009-06-25-eskom-granted-a-313-tariff-increase | F6: 29 Oct 2026 | G6: Effective 1 July 2009 (mid-year).
A7: 6 | B7: Mail & Guardian, 25 Mar 2009, Inflation up 8,6% in February | C7: Secondary | D7: 2008 CPI 11.5% and CPIX 11.3% | E7: https://mg.co.za/article/2009-03-25-inflation-up-86-in-february/ | F7: 29 Oct 2026 | G7: Separates CPIX from headline CPI.
A8: 7 | B8: Mail & Guardian, 22 Jun 2011, Consumer price index for May up at 4.6% | C8: Secondary | D8: CPI 2008 11.5%, 2009 7.1%, 2010 4.3% | E8: https://mg.co.za/article/2011-06-22-consumer-price-index-for-may-up-at-46/ | F8: 29 Oct 2026 | G8: Agrees with Stats SA table.
A9: 8 | B9: Business Times / Sunday Times, 10 Mar 2019, Nersa has starved Eskom of papgeld | C9: Secondary | D9: 2010 to 2012 increases (24.8, 25.8, 25.9 revised to 16); 2019/20 9.4%; later 8.1% and 5.2% | E9: https://www.pressreader.com/south-africa/sunday-times-1107/20190310/282376925893489 | F9: 29 Oct 2026 | G9: Reports 8.1% for 2020/21; your file has 6.9%, check.
A10: 9 | B10: MyBroadband, Eskom electricity prices 1994 to 2020 | C10: Secondary (from Eskom tariff books) | D10: 2010: 41.57 c/kWh, 24.80%; 2011: 52.30 c/kWh, 25.20% average price increase | E10: https://mybroadband.co.za/news/energy/362660-eskom-electricity-prices-1994-to-2020.html | F10: 29 Oct 2026 | G10: Average price increase can differ from the approved increase.
A11: 10 | B11: Our Power, Eskom Tariff Increase History | C11: Secondary compilation | D11: Annual increases and average c/kWh (for example 2010 to 2013, 2018) | E11: https://www.ourpower.co.za/tools/eskom-tariff-history | F11: 29 Oct 2026 | G11: Lists 234 c/kWh for 2026; your file has 226.
A12: 11 | B12: Sowetan, 9 Sep 2026, Eskom entering death spiral | C12: Secondary | D12: 5.23% (2018), 9.61% (2022/23), 18.65% (2023/24), 12.74% (2024/25) | E12: https://www.sowetan.co.za/news/2026-09-09-eskom-entering-death-spiral-as-higher-costs-push-consumers-to-alternative-energy-sources/ | F12: 29 Oct 2026
A13: 12 | B13: SavePower, Eskom Electricity Tariffs 2025 | C13: Secondary | D13: 5.23%, 9.61%, 18.65%; shows 15.06% for 2021/22 | E13: https://www.savepower.co.za/eskom-electricity-tariffs.html | F13: 29 Oct 2026 | G13: Conflicts with 15.63% for 2021/22.
A14: 13 | B14: PowerOptimal, 2022 update | C14: Secondary | D14: 2021/22: 15.63%; 2022/23: 9.61% | E14: https://poweroptimal.com/2021-update-eskom-tariff-increases-vs-inflation-since-1988/ | F14: 29 Oct 2026
A15: 14 | B15: PowerOptimal, 2024 update | C15: Secondary | D15: 2023: 18.7%; 2024: 12.7% | E15: https://poweroptimal.com/2024-update-eskom-tariff-increases-vs-inflation-since-1988-with-projections-to-2026/ | F15: 29 Oct 2026
A16: 15 | B16: News24, 12 Jan 2023, Nersa approves 18.65% electricity tariff hike | C16: Secondary | D16: 2023/24: 18.65% | E16: https://www.news24.com/fin24/Economy/nersa-approves-1865-electricity-tariff-hike-for-eskom-20230112 | F16: 29 Oct 2026
A17: 16 | B17: Engineering News, 30 Jan 2025, Nersa approves tariff hike for April 1 | C17: Secondary | D17: 2025/26: 12.74% | E17: https://www.engineeringnews.co.za/article/nersa-approves-tariff-hike-for-april-1-as-eskom-reports-r16bn-interim-profit-2025-01-30 | F17: 29 Oct 2026
A18: 17 | B18: Engineering News, 10 Mar 2026, Nersa approves higher electricity hikes for 2026/27 | C18: Secondary | D18: 2026/27: 8.76% after the R54.7bn error | E18: https://www.engineeringnews.co.za/article/nersa-approves-higher-electricity-hikes-for-202627-after-r547bn-error-2026-03-10 | F18: 29 Oct 2026
A19: 18 | B19: BusinessTech, Eskom's shocking annual price hike since 2007 | C19: Secondary compilation | D19: Cross-check of annual increases (used for 2015/16) | E19: https://businesstech.co.za/news/energy/91216/eskoms-shocking-annual-price-hike-since-2007/ | F19: 29 Oct 2026 | G19: Content not re-read in full this session.
A20: 19 | B20: Citizen / Lowvelder local news | C20: Secondary | D20: 2015/16 12.69%, 2016/17 9.4% (as noted in the earlier starter file) | E20: https://citizen.co.za/lowvelder/?p=318316 | F20: 29 Oct 2026 | G20: Content not re-read in full this session.
A21: 20 | B21: Daily Investor, South Africans will pay 10 times for electricity in 2027 | C21: Secondary | D21: 2007/08 5.9%; average price definitions | E21: https://dailyinvestor.com/energy/155975/south-africans-will-pay-10-times-for-electricity-in-2027-than-they-did-in-2008/ | F21: 29 Oct 2026 | G21: Site blocked full-page access; search snippet only.
A22: 21 | B22: Codera Analytics, Historical Eskom electricity tariff increases | C22: Secondary | D22: Alternative average price series (19.59 c/kWh in 2008/09) | E22: https://codera.co.za/historical-eskom-electricity-tariffs-increases-in-sa/ | F22: 29 Oct 2026 | G22: Different tariff definition from other sources.
A23: 22 | B23: Stats SA, Municipal finances and electricity: 11 years in perspective | C23: Primary (analysis) | D23: Municipal tariff increases differ from direct-customer increases | E23: https://www.statssa.gov.za/?p=15612 | F23: 29 Oct 2026 | G23: For example, 2017/18 municipal increase was about 0.3%.
